.DS_Store
redlist/__init__.py
redlist/add_todo.py
redlist/auto_finish.py
redlist/category.py
redlist/create_table.py
redlist/del_todo.py
redlist/duecheck.py
redlist/list.py
redlist/logo.py
redlist/ls.py
redlist/main.py
redlist/modify.py
redlist-0.0.8.dist-info/METADATA
redlist-0.0.8.dist-info/RECORD
redlist-0.0.8.dist-info/WHEEL
redlist-0.0.8.dist-info/entry_points.txt
redlist-0.0.8.dist-info/top_level.txt
