Metadata-Version: 2.1
Name: redlist
Version: 0.0.8
Summary: A simple schedule managing cli app
Home-page: https://github.com/Ramenseller/RedList
Author: Hayeong Lee
Author-email: bb.kiera@gmail.com
License: MIT LICENSE
Download-URL: https://github.com/Ramenseller/RedList/archive/master.tar.gz
Keywords: todo list,todo cli,task manager
Platform: UNKNOWN
Classifier: Environment :: Console
Classifier: License :: OSI Approved :: MIT License
Classifier: Programming Language :: Python :: 3.4
Classifier: Programming Language :: Python :: 3.5
Classifier: Programming Language :: Python :: 3.6
Requires-Dist: inquirer
Requires-Dist: prettytable
Requires-Dist: colorama
